airlift/__init__.py
airlift/commands/__init__.py
airlift/commands/check.py
airlift/commands/import_variables.py
airlift/commands/logs.py
airlift/commands/pause.py
airlift/commands/remove.py
airlift/commands/run_dag.py
airlift/commands/start.py
airlift/commands/status.py
airlift/config/__init__.py
airlift/config/airlift/config.yaml
airlift/config/airlift/required_software.yaml
airlift/config/config.py
airlift/config/docker/Dockerfile
airlift/config/docker/final/.gitkeep
airlift/config/helm/values.yaml
airlift/config/kind/cluster.yaml
airlift/main.py
airlift/utils/__init__.py
airlift/utils/airflow.py
airlift/utils/airlift.py
airlift/utils/command.py
airlift/utils/docker.py
airlift/utils/file.py
airlift/utils/helm.py
airlift/utils/kind.py
airlift/utils/kubernetes.py
airlift/utils/parser.py
airlift-0.4.0.dist-info/LICENSE
airlift-0.4.0.dist-info/METADATA
airlift-0.4.0.dist-info/WHEEL
airlift-0.4.0.dist-info/entry_points.txt
airlift-0.4.0.dist-info/RECORD
