Metadata-Version: 2.1
Name: airlift
Version: 0.4.0
Summary: A CLI for creating a flexible Apache Airflow local development environment
Author: jered.little
Author-email: jeredlittle1996@gmail.com
Requires-Python: >=3.9,<4.0
Classifier: Programming Language :: Python :: 3
Classifier: Programming Language :: Python :: 3.9
Classifier: Programming Language :: Python :: 3.10
Classifier: Programming Language :: Python :: 3.11
Requires-Dist: argparse (>=1.4.0,<2.0.0)
Requires-Dist: dotmap (>=1.3.30,<2.0.0)
Requires-Dist: halo (>=0.0.31,<0.0.32)
Requires-Dist: hiyapyco (>=0.5.1,<0.6.0)
Requires-Dist: jinja2 (>=3.1.2,<4.0.0)
Requires-Dist: pyyaml (>=6.0,<7.0)
Requires-Dist: requests (>=2.30.0,<3.0.0)
